[
 {
   "Div": "F1",
   "Date": "21/08/2020",
   "Time": "18:00",
   "HomeTeam": "Bordeaux",
   "AwayTeam": "Nantes",
   "FTHG": 0,
   "FTAG": 0,
   "FTR": "D",
   "HTHG": 0,
   "HTAG": 0,
   "HTR": "D",
   "HS": 5,
   "AS": 6,
   "HST": 1,
   "AST": 1,
   "HF": 10,
   "AF": 15,
   "HC": 2,
   "AC": 3,
   "HY": 2,
   "AY": 3,
   "HR": 1,
   "AR": 0,
   "B365H": 2.4,
   "B365D": 3,
   "B365A": 3.25,
   "BWH": 2.4,
   "BWD": 3,
   "BWA": 3.3,
   "IWH": 2.5,
   "IWD": 2.8,
   "IWA": 3.25,
   "PSH": 2.48,
   "PSD": 3.03,
   "PSA": 3.33,
   "WHH": 2.45,
   "WHD": 3,
   "WHA": 3.1,
   "VCH": 2.45,
   "VCD": 2.88,
   "VCA": 3.3,
   "MaxH": 2.59,
   "MaxD": 3.13,
   "MaxA": 3.38,
   "AvgH": 2.47,
   "AvgD": 2.95,
   "AvgA": 3.25,
   "B365>2.5": 3,
   "B365<2.5": 1.4,
   "P>2.5": 2.91,
   "P<2.5": 1.45,
   "Max>2.5": 3.1,
   "Max<2.5": 1.46,
   "Avg>2.5": 2.85,
   "Avg<2.5": 1.42,
   "AHh": -0.25,
   "B365AHH": 2.1,
   "B365AHA": 1.8,
   "PAHH": 2.09,
   "PAHA": 1.83,
   "MaxAHH": 2.16,
   "MaxAHA": 1.84,
   "AvgAHH": 2.08,
   "AvgAHA": 1.79,
   "B365CH": 2.62,
   "B365CD": 2.87,
   "B365CA": 3.1,
   "BWCH": 2.75,
   "BWCD": 2.9,
   "BWCA": 2.95,
   "IWCH": 2.7,
   "IWCD": 2.8,
   "IWCA": 3,
   "PSCH": 2.71,
   "PSCD": 2.97,
   "PSCA": 3.02,
   "WHCH": 2.62,
   "WHCD": 3,
   "WHCA": 2.9,
   "VCCH": 2.63,
   "VCCD": 2.88,
   "VCCA": 3,
   "MaxCH": 2.8,
   "MaxCD": 3.08,
   "MaxCA": 3.25,
   "AvgCH": 2.65,
   "AvgCD": 2.93,
   "AvgCA": 3.01,
   "B365C>2.5": 2.75,
   "B365C<2.5": 1.44,
   "PC>2.5": 2.89,
   "PC<2.5": 1.46,
   "MaxC>2.5": 2.9,
   "MaxC<2.5": 1.49,
   "AvgC>2.5": 2.79,
   "AvgC<2.5": 1.43,
   "AHCh": 0,
   "B365CAHH": 1.86,
   "B365CAHA": 2.04,
   "PCAHH": 1.85,
   "PCAHA": 2.07,
   "MaxCAHH": 1.9,
   "MaxCAHA": 2.24,
   "AvgCAHH": 1.82,
   "AvgCAHA": 2.05
 },
 {
   "Div": "F1",
   "Date": "22/08/2020",
   "Time": "16:00",
   "HomeTeam": "Dijon",
   "AwayTeam": "Angers",
   "FTHG": 0,
   "FTAG": 1,
   "FTR": "A",
   "HTHG": 0,
   "HTAG": 1,
   "HTR": "A",
   "HS": 9,
   "AS": 12,
   "HST": 1,
   "AST": 4,
   "HF": 15,
   "AF": 8,
   "HC": 3,
   "AC": 9,
   "HY": 0,
   "AY": 0,
   "HR": 0,
   "AR": 0,
   "B365H": 2.7,
   "B365D": 3.1,
   "B365A": 2.8,
   "BWH": 2.75,
   "BWD": 3,
   "BWA": 2.8,
   "IWH": 2.75,
   "IWD": 2.9,
   "IWA": 2.8,
   "PSH": 2.79,
   "PSD": 3.09,
   "PSA": 2.84,
   "WHH": 2.7,
   "WHD": 3.1,
   "WHA": 2.75,
   "VCH": 2.7,
   "VCD": 3,
   "VCA": 2.8,
   "MaxH": 2.86,
   "MaxD": 3.22,
   "MaxA": 2.92,
   "AvgH": 2.73,
   "AvgD": 3.07,
   "AvgA": 2.77,
   "B365>2.5": 2.37,
   "B365<2.5": 1.57,
   "P>2.5": 2.51,
   "P<2.5": 1.57,
   "Max>2.5": 2.57,
   "Max<2.5": 1.63,
   "Avg>2.5": 2.4,
   "Avg<2.5": 1.57,
   "AHh": 0,
   "B365AHH": 1.93,
   "B365AHA": 1.97,
   "PAHH": 1.94,
   "PAHA": 1.98,
   "MaxAHH": 1.98,
   "MaxAHA": 2.01,
   "AvgAHH": 1.91,
   "AvgAHA": 1.95,
   "B365CH": 3.25,
   "B365CD": 3.1,
   "B365CA": 2.35,
   "BWCH": 3.1,
   "BWCD": 3.1,
   "BWCA": 2.45,
   "IWCH": 3.3,
   "IWCD": 2.85,
   "IWCA": 2.45,
   "PSCH": 3.36,
   "PSCD": 3.07,
   "PSCA": 2.44,
   "WHCH": 3.25,
   "WHCD": 3,
   "WHCA": 2.38,
   "VCCH": 3.4,
   "VCCD": 2.9,
   "VCCA": 2.38,
   "MaxCH": 3.46,
   "MaxCD": 3.17,
   "MaxCA": 2.53,
   "AvgCH": 3.3,
   "AvgCD": 3.02,
   "AvgCA": 2.39,
   "B365C>2.5": 2.75,
   "B365C<2.5": 1.44,
   "PC>2.5": 2.72,
   "PC<2.5": 1.5,
   "MaxC>2.5": 2.86,
   "MaxC<2.5": 1.56,
   "AvgC>2.5": 2.61,
   "AvgC<2.5": 1.49,
   "AHCh": 0.25,
   "B365CAHH": 1.86,
   "B365CAHA": 2.07,
   "PCAHH": 1.85,
   "PCAHA": 2.06,
   "MaxCAHH": 1.88,
   "MaxCAHA": 2.08,
   "AvgCAHH": 1.83,
   "AvgCAHA": 2.03
 },
 {
   "Div": "F1",
   "Date": "22/08/2020",
   "Time": "20:00",
   "HomeTeam": "Lille",
   "AwayTeam": "Rennes",
   "FTHG": 1,
   "FTAG": 1,
   "FTR": "D",
   "HTHG": 1,
   "HTAG": 0,
   "HTR": "H",
   "HS": 5,
   "AS": 16,
   "HST": 1,
   "AST": 3,
   "HF": 12,
   "AF": 16,
   "HC": 4,
   "AC": 2,
   "HY": 0,
   "AY": 1,
   "HR": 1,
   "AR": 1,
   "B365H": 2.3,
   "B365D": 3.2,
   "B365A": 3.3,
   "BWH": 2.3,
   "BWD": 3.2,
   "BWA": 3.3,
   "IWH": 2.3,
   "IWD": 3,
   "IWA": 3.35,
   "PSH": 2.3,
   "PSD": 3.22,
   "PSA": 3.47,
   "WHH": 2.25,
   "WHD": 3.2,
   "WHA": 3.3,
   "VCH": 2.25,
   "VCD": 3.13,
   "VCA": 3.4,
   "MaxH": 2.38,
   "MaxD": 3.34,
   "MaxA": 3.6,
   "AvgH": 2.27,
   "AvgD": 3.18,
   "AvgA": 3.36,
   "B365>2.5": 2.3,
   "B365<2.5": 1.61,
   "P>2.5": 2.37,
   "P<2.5": 1.64,
   "Max>2.5": 2.43,
   "Max<2.5": 1.69,
   "Avg>2.5": 2.29,
   "Avg<2.5": 1.62,
   "AHh": -0.25,
   "B365AHH": 1.97,
   "B365AHA": 1.93,
   "PAHH": 1.97,
   "PAHA": 1.95,
   "MaxAHH": 2.02,
   "MaxAHA": 1.96,
   "AvgAHH": 1.95,
   "AvgAHA": 1.91,
   "B365CH": 1.85,
   "B365CD": 3.4,
   "B365CA": 4.2,
   "BWCH": 1.95,
   "BWCD": 3.3,
   "BWCA": 4.33,
   "IWCH": 1.9,
   "IWCD": 3.2,
   "IWCA": 4.4,
   "PSCH": 1.92,
   "PSCD": 3.47,
   "PSCA": 4.52,
   "WHCH": 1.85,
   "WHCD": 3.4,
   "WHCA": 4.4,
   "VCCH": 1.87,
   "VCCD": 3.4,
   "VCCA": 4.4,
   "MaxCH": 1.97,
   "MaxCD": 3.55,
   "MaxCA": 4.7,
   "AvgCH": 1.89,
   "AvgCD": 3.38,
   "AvgCA": 4.38,
   "B365C>2.5": 2.2,
   "B365C<2.5": 1.66,
   "PC>2.5": 2.33,
   "PC<2.5": 1.66,
   "MaxC>2.5": 2.38,
   "MaxC<2.5": 1.76,
   "AvgC>2.5": 2.26,
   "AvgC<2.5": 1.64,
   "AHCh": -0.5,
   "B365CAHH": 1.9,
   "B365CAHA": 2.03,
   "PCAHH": 1.92,
   "PCAHA": 2,
   "MaxCAHH": 1.95,
   "MaxCAHA": 2.05,
   "AvgCAHH": 1.89,
   "AvgCAHA": 1.96
 },
 {
   "Div": "F1",
   "Date": "23/08/2020",
   "Time": "12:00",
   "HomeTeam": "Monaco",
   "AwayTeam": "Reims",
   "FTHG": 2,
   "FTAG": 2,
   "FTR": "D",
   "HTHG": 1,
   "HTAG": 2,
   "HTR": "A",
   "HS": 22,
   "AS": 9,
   "HST": 5,
   "AST": 3,
   "HF": 8,
   "AF": 14,
   "HC": 8,
   "AC": 1,
   "HY": 1,
   "AY": 3,
   "HR": 0,
   "AR": 0,
   "B365H": 1.9,
   "B365D": 3.4,
   "B365A": 4.33,
   "BWH": 1.91,
   "BWD": 3.5,
   "BWA": 4.2,
   "IWH": 1.95,
   "IWD": 3.25,
   "IWA": 4.2,
   "PSH": 1.95,
   "PSD": 3.53,
   "PSA": 4.24,
   "WHH": 1.88,
   "WHD": 3.4,
   "WHA": 4.2,
   "VCH": 1.87,
   "VCD": 3.25,
   "VCA": 4.4,
   "MaxH": 2,
   "MaxD": 3.65,
   "MaxA": 4.5,
   "AvgH": 1.92,
   "AvgD": 3.45,
   "AvgA": 4.16,
   "B365>2.5": 2.2,
   "B365<2.5": 1.66,
   "P>2.5": 2.32,
   "P<2.5": 1.66,
   "Max>2.5": 2.38,
   "Max<2.5": 1.72,
   "Avg>2.5": 2.25,
   "Avg<2.5": 1.65,
   "AHh": -0.5,
   "B365AHH": 1.93,
   "B365AHA": 1.97,
   "PAHH": 1.95,
   "PAHA": 1.97,
   "MaxAHH": 1.95,
   "MaxAHA": 2,
   "AvgAHH": 1.91,
   "AvgAHA": 1.94,
   "B365CH": 1.85,
   "B365CD": 3.4,
   "B365CA": 4.33,
   "BWCH": 1.91,
   "BWCD": 3.5,
   "BWCA": 4.2,
   "IWCH": 1.95,
   "IWCD": 3.2,
   "IWCA": 4.3,
   "PSCH": 1.95,
   "PSCD": 3.43,
   "PSCA": 4.42,
   "WHCH": 1.85,
   "WHCD": 3.5,
   "WHCA": 4.33,
   "VCCH": 1.9,
   "VCCD": 3.3,
   "VCCA": 4.4,
   "MaxCH": 1.98,
   "MaxCD": 3.64,
   "MaxCA": 4.71,
   "AvgCH": 1.92,
   "AvgCD": 3.37,
   "AvgCA": 4.25,
   "B365C>2.5": 2.3,
   "B365C<2.5": 1.61,
   "PC>2.5": 2.4,
   "PC<2.5": 1.63,
   "MaxC>2.5": 2.43,
   "MaxC<2.5": 1.69,
   "AvgC>2.5": 2.29,
   "AvgC<2.5": 1.62,
   "AHCh": -0.5,
   "B365CAHH": 1.95,
   "B365CAHA": 1.98,
   "PCAHH": 1.95,
   "PCAHA": 1.97,
   "MaxCAHH": 1.96,
   "MaxCAHA": 1.99,
   "AvgCAHH": 1.92,
   "AvgCAHA": 1.92
 },
 {
   "Div": "F1",
   "Date": "23/08/2020",
   "Time": "14:00",
   "HomeTeam": "Lorient",
   "AwayTeam": "Strasbourg",
   "FTHG": 3,
   "FTAG": 1,
   "FTR": "H",
   "HTHG": 0,
   "HTAG": 1,
   "HTR": "A",
   "HS": 10,
   "AS": 7,
   "HST": 7,
   "AST": 1,
   "HF": 17,
   "AF": 10,
   "HC": 6,
   "AC": 1,
   "HY": 3,
   "AY": 2,
   "HR": 0,
   "AR": 0,
   "B365H": 2.5,
   "B365D": 3.2,
   "B365A": 3,
   "BWH": 2.6,
   "BWD": 3.2,
   "BWA": 2.85,
   "IWH": 2.55,
   "IWD": 2.95,
   "IWA": 2.95,
   "PSH": 2.62,
   "PSD": 3.19,
   "PSA": 2.96,
   "WHH": 2.5,
   "WHD": 3.2,
   "WHA": 2.88,
   "VCH": 2.55,
   "VCD": 3,
   "VCA": 2.88,
   "MaxH": 2.75,
   "MaxD": 3.32,
   "MaxA": 3.05,
   "AvgH": 2.56,
   "AvgD": 3.13,
   "AvgA": 2.91,
   "B365>2.5": 2.3,
   "B365<2.5": 1.61,
   "P>2.5": 2.38,
   "P<2.5": 1.64,
   "Max>2.5": 2.43,
   "Max<2.5": 1.69,
   "Avg>2.5": 2.32,
   "Avg<2.5": 1.61,
   "AHh": 0,
   "B365AHH": 1.83,
   "B365AHA": 2.07,
   "PAHH": 1.84,
   "PAHA": 2.08,
   "MaxAHH": 1.94,
   "MaxAHA": 2.12,
   "AvgAHH": 1.82,
   "AvgAHA": 2.05,
   "B365CH": 2.4,
   "B365CD": 3.1,
   "B365CA": 3.1,
   "BWCH": 2.5,
   "BWCD": 3.1,
   "BWCA": 3.1,
   "IWCH": 2.5,
   "IWCD": 2.95,
   "IWCA": 3.15,
   "PSCH": 2.45,
   "PSCD": 3.15,
   "PSCA": 3.25,
   "WHCH": 2.4,
   "WHCD": 3.1,
   "WHCA": 3.1,
   "VCCH": 2.4,
   "VCCD": 3,
   "VCCA": 3.2,
   "MaxCH": 2.54,
   "MaxCD": 3.3,
   "MaxCA": 3.26,
   "AvgCH": 2.43,
   "AvgCD": 3.09,
   "AvgCA": 3.15,
   "B365C>2.5": 2.5,
   "B365C<2.5": 1.53,
   "PC>2.5": 2.52,
   "PC<2.5": 1.57,
   "MaxC>2.5": 2.52,
   "MaxC<2.5": 1.67,
   "AvgC>2.5": 2.4,
   "AvgC<2.5": 1.58,
   "AHCh": -0.25,
   "B365CAHH": 2.08,
   "B365CAHA": 1.85,
   "PCAHH": 2.09,
   "PCAHA": 1.83,
   "MaxCAHH": 2.14,
   "MaxCAHA": 1.86,
   "AvgCAHH": 2.07,
   "AvgCAHA": 1.8
 },
 {
   "Div": "F1",
   "Date": "23/08/2020",
   "Time": "14:00",
   "HomeTeam": "Nimes",
   "AwayTeam": "Brest",
   "FTHG": 4,
   "FTAG": 0,
   "FTR": "H",
   "HTHG": 2,
   "HTAG": 0,
   "HTR": "H",
   "HS": 12,
   "AS": 10,
   "HST": 5,
   "AST": 3,
   "HF": 14,
   "AF": 17,
   "HC": 4,
   "AC": 4,
   "HY": 2,
   "AY": 3,
   "HR": 0,
   "AR": 1,
   "B365H": 2.3,
   "B365D": 3.2,
   "B365A": 3.3,
   "BWH": 2.25,
   "BWD": 3.3,
   "BWA": 3.3,
   "IWH": 2.3,
   "IWD": 3.15,
   "IWA": 3.3,
   "PSH": 2.29,
   "PSD": 3.39,
   "PSA": 3.32,
   "WHH": 2.25,
   "WHD": 3.3,
   "WHA": 3.25,
   "VCH": 2.2,
   "VCD": 3.25,
   "VCA": 3.3,
   "MaxH": 2.35,
   "MaxD": 3.48,
   "MaxA": 3.46,
   "AvgH": 2.24,
   "AvgD": 3.32,
   "AvgA": 3.27,
   "B365>2.5": 2,
   "B365<2.5": 1.8,
   "P>2.5": 2.11,
   "P<2.5": 1.79,
   "Max>2.5": 2.17,
   "Max<2.5": 1.85,
   "Avg>2.5": 2.07,
   "Avg<2.5": 1.76,
   "AHh": -0.25,
   "B365AHH": 1.95,
   "B365AHA": 1.95,
   "PAHH": 1.98,
   "PAHA": 1.94,
   "MaxAHH": 1.98,
   "MaxAHA": 1.98,
   "AvgAHH": 1.93,
   "AvgAHA": 1.92,
   "B365CH": 2.25,
   "B365CD": 3.2,
   "B365CA": 3.4,
   "BWCH": 2.25,
   "BWCD": 3.3,
   "BWCA": 3.3,
   "IWCH": 2.3,
   "IWCD": 3.15,
   "IWCA": 3.2,
   "PSCH": 2.35,
   "PSCD": 3.38,
   "PSCA": 3.2,
   "WHCH": 2.25,
   "WHCD": 3.3,
   "WHCA": 3.2,
   "VCCH": 2.3,
   "VCCD": 3.3,
   "VCCA": 3.13,
   "MaxCH": 2.4,
   "MaxCD": 3.5,
   "MaxCA": 3.47,
   "AvgCH": 2.29,
   "AvgCD": 3.3,
   "AvgCA": 3.2,
   "B365C>2.5": 2,
   "B365C<2.5": 1.8,
   "PC>2.5": 2.05,
   "PC<2.5": 1.85,
   "MaxC>2.5": 2.15,
   "MaxC<2.5": 1.9,
   "AvgC>2.5": 1.99,
   "AvgC<2.5": 1.82,
   "AHCh": -0.25,
   "B365CAHH": 2.02,
   "B365CAHA": 1.91,
   "PCAHH": 2.03,
   "PCAHA": 1.89,
   "MaxCAHH": 2.04,
   "MaxCAHA": 1.92,
   "AvgCAHH": 1.98,
   "AvgCAHA": 1.88
 },
 {
   "Div": "F1",
   "Date": "23/08/2020",
   "Time": "16:00",
   "HomeTeam": "Nice",
   "AwayTeam": "Lens",
   "FTHG": 2,
   "FTAG": 1,
   "FTR": "H",
   "HTHG": 1,
   "HTAG": 1,
   "HTR": "D",
   "HS": 4,
   "AS": 17,
   "HST": 2,
   "AST": 4,
   "HF": 17,
   "AF": 18,
   "HC": 1,
   "AC": 7,
   "HY": 2,
   "AY": 3,
   "HR": 0,
   "AR": 0,
   "B365H": 2,
   "B365D": 3.3,
   "B365A": 4,
   "BWH": 1.95,
   "BWD": 3.5,
   "BWA": 3.9,
   "IWH": 2.05,
   "IWD": 3.2,
   "IWA": 3.85,
   "PSH": 2.05,
   "PSD": 3.36,
   "PSA": 4.06,
   "WHH": 2,
   "WHD": 3.4,
   "WHA": 3.8,
   "VCH": 2,
   "VCD": 3.25,
   "VCA": 3.8,
   "MaxH": 2.12,
   "MaxD": 3.54,
   "MaxA": 4.25,
   "AvgH": 2.02,
   "AvgD": 3.34,
   "AvgA": 3.88,
   "B365>2.5": 2.1,
   "B365<2.5": 1.72,
   "P>2.5": 2.18,
   "P<2.5": 1.75,
   "Max>2.5": 2.22,
   "Max<2.5": 1.81,
   "Avg>2.5": 2.11,
   "Avg<2.5": 1.73,
   "AHh": -0.5,
   "B365AHH": 2.04,
   "B365AHA": 1.86,
   "PAHH": 2.05,
   "PAHA": 1.87,
   "MaxAHH": 2.08,
   "MaxAHA": 1.88,
   "AvgAHH": 2.03,
   "AvgAHA": 1.82,
   "B365CH": 2,
   "B365CD": 3.3,
   "B365CA": 3.9,
   "BWCH": 2.05,
   "BWCD": 3.25,
   "BWCA": 3.9,
   "IWCH": 2,
   "IWCD": 3.15,
   "IWCA": 4,
   "PSCH": 2.02,
   "PSCD": 3.38,
   "PSCA": 4.16,
   "WHCH": 1.95,
   "WHCD": 3.2,
   "WHCA": 4.2,
   "VCCH": 1.95,
   "VCCD": 3.3,
   "VCCA": 4.1,
   "MaxCH": 2.06,
   "MaxCD": 3.45,
   "MaxCA": 4.55,
   "AvgCH": 2,
   "AvgCD": 3.3,
   "AvgCA": 4.03,
   "B365C>2.5": 2.2,
   "B365C<2.5": 1.66,
   "PC>2.5": 2.25,
   "PC<2.5": 1.7,
   "MaxC>2.5": 2.3,
   "MaxC<2.5": 1.76,
   "AvgC>2.5": 2.18,
   "AvgC<2.5": 1.69,
   "AHCh": -0.5,
   "B365CAHH": 2.02,
   "B365CAHA": 1.91,
   "PCAHH": 2.02,
   "PCAHA": 1.9,
   "MaxCAHH": 2.05,
   "MaxCAHA": 1.92,
   "AvgCAHH": 2,
   "AvgCAHA": 1.86
 },
 {
   "Div": "F1",
   "Date": "28/08/2020",
   "Time": "20:00",
   "HomeTeam": "Lyon",
   "AwayTeam": "Dijon",
   "FTHG": 4,
   "FTAG": 1,
   "FTR": "H",
   "HTHG": 3,
   "HTAG": 1,
   "HTR": "H",
   "HS": 27,
   "AS": 6,
   "HST": 12,
   "AST": 2,
   "HF": 12,
   "AF": 7,
   "HC": 13,
   "AC": 2,
   "HY": 3,
   "AY": 3,
   "HR": 0,
   "AR": 0,
   "B365H": 1.28,
   "B365D": 5.75,
   "B365A": 9,
   "BWH": 1.3,
   "BWD": 5.5,
   "BWA": 10,
   "IWH": 1.33,
   "IWD": 5.25,
   "IWA": 10,
   "PSH": 1.31,
   "PSD": 5.68,
   "PSA": 10.21,
   "WHH": 1.27,
   "WHD": 5.5,
   "WHA": 11,
   "VCH": 1.29,
   "VCD": 5.25,
   "VCA": 11,
   "MaxH": 1.35,
   "MaxD": 6.05,
   "MaxA": 11.75,
   "AvgH": 1.3,
   "AvgD": 5.41,
   "AvgA": 10.01,
   "B365>2.5": 1.66,
   "B365<2.5": 2.2,
   "P>2.5": 1.68,
   "P<2.5": 2.3,
   "Max>2.5": 1.74,
   "Max<2.5": 2.39,
   "Avg>2.5": 1.66,
   "Avg<2.5": 2.24,
   "AHh": -1.5,
   "B365AHH": 1.96,
   "B365AHA": 1.94,
   "PAHH": 2.04,
   "PAHA": 1.88,
   "MaxAHH": 2,
   "MaxAHA": 2.01,
   "AvgAHH": 1.92,
   "AvgAHA": 1.93,
   "B365CH": 1.25,
   "B365CD": 5.5,
   "B365CA": 12,
   "BWCH": 1.28,
   "BWCD": 5.75,
   "BWCA": 10.5,
   "IWCH": 1.3,
   "IWCD": 6,
   "IWCA": 9.5,
   "PSCH": 1.25,
   "PSCD": 6.32,
   "PSCA": 13.01,
   "WHCH": 1.22,
   "WHCD": 6,
   "WHCA": 13,
   "VCCH": 1.25,
   "VCCD": 5.75,
   "VCCA": 11.5,
   "MaxCH": 1.3,
   "MaxCD": 6.45,
   "MaxCA": 13.5,
   "AvgCH": 1.26,
   "AvgCD": 5.99,
   "AvgCA": 11.31,
   "B365C>2.5": 1.57,
   "B365C<2.5": 2.37,
   "PC>2.5": 1.61,
   "PC<2.5": 2.46,
   "MaxC>2.5": 1.65,
   "MaxC<2.5": 2.55,
   "AvgC>2.5": 1.57,
   "AvgC<2.5": 2.38,
   "AHCh": -1.75,
   "B365CAHH": 2.01,
   "B365CAHA": 1.89,
   "PCAHH": 2,
   "PCAHA": 1.92,
   "MaxCAHH": 2.06,
   "MaxCAHA": 1.92,
   "AvgCAHH": 2,
   "AvgCAHA": 1.86
 },
 {
   "Div": "F1",
   "Date": "29/08/2020",
   "Time": "16:00",
   "HomeTeam": "Rennes",
   "AwayTeam": "Montpellier",
   "FTHG": 2,
   "FTAG": 1,
   "FTR": "H",
   "HTHG": 1,
   "HTAG": 0,
   "HTR": "H",
   "HS": 16,
   "AS": 11,
   "HST": 7,
   "AST": 3,
   "HF": 18,
   "AF": 16,
   "HC": 2,
   "AC": 1,
   "HY": 3,
   "AY": 2,
   "HR": 1,
   "AR": 1,
   "B365H": 2,
   "B365D": 3.3,
   "B365A": 3.8,
   "BWH": 2,
   "BWD": 3.3,
   "BWA": 4,
   "IWH": 2.1,
   "IWD": 3.1,
   "IWA": 3.95,
   "PSH": 2.07,
   "PSD": 3.31,
   "PSA": 3.97,
   "WHH": 2,
   "WHD": 3.3,
   "WHA": 3.9,
   "VCH": 2,
   "VCD": 3.25,
   "VCA": 4,
   "MaxH": 2.1,
   "MaxD": 3.48,
   "MaxA": 4.15,
   "AvgH": 2.04,
   "AvgD": 3.28,
   "AvgA": 3.9,
   "B365>2.5": 2.3,
   "B365<2.5": 1.61,
   "P>2.5": 2.38,
   "P<2.5": 1.64,
   "Max>2.5": 2.43,
   "Max<2.5": 1.7,
   "Avg>2.5": 2.31,
   "Avg<2.5": 1.62,
   "AHh": -0.5,
   "B365AHH": 2.05,
   "B365AHA": 1.85,
   "PAHH": 2.07,
   "PAHA": 1.85,
   "MaxAHH": 2.07,
   "MaxAHA": 1.88,
   "AvgAHH": 2.03,
   "AvgAHA": 1.82,
   "B365CH": 1.8,
   "B365CD": 3.5,
   "B365CA": 4.5,
   "BWCH": 1.8,
   "BWCD": 3.5,
   "BWCA": 4.75,
   "IWCH": 1.85,
   "IWCD": 3.3,
   "IWCA": 4.7,
   "PSCH": 1.86,
   "PSCD": 3.55,
   "PSCA": 4.59,
   "WHCH": 1.78,
   "WHCD": 3.5,
   "WHCA": 4.75,
   "VCCH": 1.8,
   "VCCD": 3.4,
   "VCCA": 4.8,
   "MaxCH": 1.91,
   "MaxCD": 3.66,
   "MaxCA": 5.15,
   "AvgCH": 1.84,
   "AvgCD": 3.45,
   "AvgCA": 4.59,
   "B365C>2.5": 2.3,
   "B365C<2.5": 1.61,
   "PC>2.5": 2.29,
   "PC<2.5": 1.68,
   "MaxC>2.5": 2.36,
   "MaxC<2.5": 1.76,
   "AvgC>2.5": 2.25,
   "AvgC<2.5": 1.64,
   "AHCh": -0.5,
   "B365CAHH": 1.83,
   "B365CAHA": 2.07,
   "PCAHH": 1.86,
   "PCAHA": 2.06,
   "MaxCAHH": 1.95,
   "MaxCAHA": 2.11,
   "AvgCAHH": 1.84,
   "AvgCAHA": 2.02
 },
 {
   "Div": "F1",
   "Date": "29/08/2020",
   "Time": "20:00",
   "HomeTeam": "Strasbourg",
   "AwayTeam": "Nice",
   "FTHG": 0,
   "FTAG": 2,
   "FTR": "A",
   "HTHG": 0,
   "HTAG": 1,
   "HTR": "A",
   "HS": 6,
   "AS": 3,
   "HST": 0,
   "AST": 2,
   "HF": 14,
   "AF": 11,
   "HC": 3,
   "AC": 1,
   "HY": 2,
   "AY": 6,
   "HR": 0,
   "AR": 0,
   "B365H": 2.2,
   "B365D": 3.3,
   "B365A": 3.3,
   "BWH": 2.25,
   "BWD": 3.3,
   "BWA": 3.3,
   "IWH": 2.3,
   "IWD": 3.15,
   "IWA": 3.3,
   "PSH": 2.28,
   "PSD": 3.35,
   "PSA": 3.32,
   "WHH": 2.2,
   "WHD": 3.3,
   "WHA": 3.3,
   "VCH": 2.25,
   "VCD": 3.25,
   "VCA": 3.3,
   "MaxH": 2.31,
   "MaxD": 3.52,
   "MaxA": 3.5,
   "AvgH": 2.23,
   "AvgD": 3.31,
   "AvgA": 3.31,
   "B365>2.5": 2,
   "B365<2.5": 1.8,
   "P>2.5": 2.11,
   "P<2.5": 1.8,
   "Max>2.5": 2.19,
   "Max<2.5": 1.85,
   "Avg>2.5": 2.06,
   "Avg<2.5": 1.77,
   "AHh": -0.25,
   "B365AHH": 1.95,
   "B365AHA": 1.95,
   "PAHH": 1.97,
   "PAHA": 1.95,
   "MaxAHH": 1.97,
   "MaxAHA": 1.99,
   "AvgAHH": 1.92,
   "AvgAHA": 1.94,
   "B365CH": 2.05,
   "B365CD": 3.5,
   "B365CA": 3.5,
   "BWCH": 2.25,
   "BWCD": 3.4,
   "BWCA": 3.2,
   "IWCH": 2.1,
   "IWCD": 3.2,
   "IWCA": 3.7,
   "PSCH": 2.09,
   "PSCD": 3.39,
   "PSCA": 3.78,
   "WHCH": 2.05,
   "WHCD": 3.4,
   "WHCA": 3.6,
   "VCCH": 2.05,
   "VCCD": 3.3,
   "VCCA": 3.7,
   "MaxCH": 2.25,
   "MaxCD": 3.6,
   "MaxCA": 3.9,
   "AvgCH": 2.09,
   "AvgCD": 3.36,
   "AvgCA": 3.63,
   "B365C>2.5": 2.1,
   "B365C<2.5": 1.72,
   "PC>2.5": 2.18,
   "PC<2.5": 1.75,
   "MaxC>2.5": 2.23,
   "MaxC<2.5": 1.83,
   "AvgC>2.5": 2.09,
   "AvgC<2.5": 1.74,
   "AHCh": -0.25,
   "B365CAHH": 1.77,
   "B365CAHA": 2.02,
   "PCAHH": 1.8,
   "PCAHA": 2.13,
   "MaxCAHH": 1.95,
   "MaxCAHA": 2.17,
   "AvgCAHH": 1.79,
   "AvgCAHA": 2.07
 },
 {
   "Div": "F1",
   "Date": "30/08/2020",
   "Time": "12:00",
   "HomeTeam": "Reims",
   "AwayTeam": "Lille",
   "FTHG": 0,
   "FTAG": 1,
   "FTR": "A",
   "HTHG": 0,
   "HTAG": 1,
   "HTR": "A",
   "HS": 4,
   "AS": 10,
   "HST": 0,
   "AST": 3,
   "HF": 20,
   "AF": 11,
   "HC": 1,
   "AC": 2,
   "HY": 4,
   "AY": 1,
   "HR": 0,
   "AR": 0,
   "B365H": 3,
   "B365D": 3.1,
   "B365A": 2.45,
   "BWH": 3.1,
   "BWD": 3,
   "BWA": 2.55,
   "IWH": 3.05,
   "IWD": 2.85,
   "IWA": 2.6,
   "PSH": 3.07,
   "PSD": 2.99,
   "PSA": 2.64,
   "WHH": 3,
   "WHD": 3,
   "WHA": 2.55,
   "VCH": 3,
   "VCD": 3,
   "VCA": 2.5,
   "MaxH": 3.15,
   "MaxD": 3.16,
   "MaxA": 2.71,
   "AvgH": 3.03,
   "AvgD": 3,
   "AvgA": 2.56,
   "B365>2.5": 2.5,
   "B365<2.5": 1.53,
   "P>2.5": 2.62,
   "P<2.5": 1.54,
   "Max>2.5": 2.68,
   "Max<2.5": 1.59,
   "Avg>2.5": 2.52,
   "Avg<2.5": 1.52,
   "AHh": 0,
   "B365AHH": 2.13,
   "B365AHA": 1.78,
   "PAHH": 2.11,
   "PAHA": 1.81,
   "MaxAHH": 2.19,
   "MaxAHA": 1.85,
   "AvgAHH": 2.11,
   "AvgAHA": 1.77,
   "B365CH": 3.1,
   "B365CD": 2.9,
   "B365CA": 2.6,
   "BWCH": 3,
   "BWCD": 3,
   "BWCA": 2.6,
   "IWCH": 3.15,
   "IWCD": 2.75,
   "IWCA": 2.6,
   "PSCH": 3.21,
   "PSCD": 2.89,
   "PSCA": 2.63,
   "WHCH": 3.1,
   "WHCD": 2.88,
   "WHCA": 2.55,
   "VCCH": 3.1,
   "VCCD": 2.9,
   "VCCA": 2.55,
   "MaxCH": 3.3,
   "MaxCD": 3.06,
   "MaxCA": 2.74,
   "AvgCH": 3.11,
   "AvgCD": 2.9,
   "AvgCA": 2.59,
   "B365C>2.5": 2.75,
   "B365C<2.5": 1.44,
   "PC>2.5": 2.9,
   "PC<2.5": 1.46,
   "MaxC>2.5": 2.95,
   "MaxC<2.5": 1.53,
   "AvgC>2.5": 2.72,
   "AvgC<2.5": 1.46,
   "AHCh": 0,
   "B365CAHH": 2.14,
   "B365CAHA": 1.77,
   "PCAHH": 2.17,
   "PCAHA": 1.77,
   "MaxCAHH": 2.2,
   "MaxCAHA": 1.83,
   "AvgCAHH": 2.13,
   "AvgCAHA": 1.76
 },
 {
   "Div": "F1",
   "Date": "30/08/2020",
   "Time": "14:00",
   "HomeTeam": "Angers",
   "AwayTeam": "Bordeaux",
   "FTHG": 0,
   "FTAG": 2,
   "FTR": "A",
   "HTHG": 0,
   "HTAG": 2,
   "HTR": "A",
   "HS": 12,
   "AS": 7,
   "HST": 2,
   "AST": 7,
   "HF": 12,
   "AF": 19,
   "HC": 5,
   "AC": 7,
   "HY": 1,
   "AY": 3,
   "HR": 0,
   "AR": 0,
   "B365H": 2.25,
   "B365D": 3.1,
   "B365A": 3.4,
   "BWH": 2.25,
   "BWD": 3.1,
   "BWA": 3.5,
   "IWH": 2.3,
   "IWD": 2.95,
   "IWA": 3.45,
   "PSH": 2.32,
   "PSD": 3.13,
   "PSA": 3.47,
   "WHH": 2.25,
   "WHD": 3.1,
   "WHA": 3.4,
   "VCH": 2.25,
   "VCD": 3,
   "VCA": 3.5,
   "MaxH": 2.4,
   "MaxD": 3.25,
   "MaxA": 3.6,
   "AvgH": 2.28,
   "AvgD": 3.1,
   "AvgA": 3.44,
   "B365>2.5": 2.5,
   "B365<2.5": 1.53,
   "P>2.5": 2.65,
   "P<2.5": 1.53,
   "Max>2.5": 2.71,
   "Max<2.5": 1.6,
   "Avg>2.5": 2.55,
   "Avg<2.5": 1.51,
   "AHh": -0.25,
   "B365AHH": 1.96,
   "B365AHA": 1.94,
   "PAHH": 1.98,
   "PAHA": 1.93,
   "MaxAHH": 1.99,
   "MaxAHA": 1.97,
   "AvgAHH": 1.94,
   "AvgAHA": 1.92,
   "B365CH": 2.2,
   "B365CD": 3,
   "B365CA": 3.75,
   "BWCH": 2.25,
   "BWCD": 3.1,
   "BWCA": 3.5,
   "IWCH": 2.25,
   "IWCD": 2.9,
   "IWCA": 3.75,
   "PSCH": 2.25,
   "PSCD": 3.05,
   "PSCA": 3.78,
   "WHCH": 2.2,
   "WHCD": 3,
   "WHCA": 3.7,
   "VCCH": 2.2,
   "VCCD": 3,
   "VCCA": 3.7,
   "MaxCH": 2.35,
   "MaxCD": 3.16,
   "MaxCA": 3.9,
   "AvgCH": 2.24,
   "AvgCD": 3.02,
   "AvgCA": 3.64,
   "B365C>2.5": 2.75,
   "B365C<2.5": 1.44,
   "PC>2.5": 2.82,
   "PC<2.5": 1.48,
   "MaxC>2.5": 2.88,
   "MaxC<2.5": 1.53,
   "AvgC>2.5": 2.69,
   "AvgC<2.5": 1.46,
   "AHCh": -0.25,
   "B365CAHH": 1.9,
   "B365CAHA": 2,
   "PCAHH": 1.91,
   "PCAHA": 2.01,
   "MaxCAHH": 2.02,
   "MaxCAHA": 2.01,
   "AvgCAHH": 1.9,
   "AvgCAHA": 1.95
 },
 {
   "Div": "F1",
   "Date": "30/08/2020",
   "Time": "14:00",
   "HomeTeam": "Metz",
   "AwayTeam": "Monaco",
   "FTHG": 0,
   "FTAG": 1,
   "FTR": "A",
   "HTHG": 0,
   "HTAG": 1,
   "HTR": "A",
   "HS": 14,
   "AS": 3,
   "HST": 4,
   "AST": 2,
   "HF": 14,
   "AF": 20,
   "HC": 10,
   "AC": 1,
   "HY": 0,
   "AY": 5,
   "HR": 0,
   "AR": 1,
   "B365H": 3.75,
   "B365D": 3.4,
   "B365A": 2,
   "BWH": 3.75,
   "BWD": 3.5,
   "BWA": 2,
   "IWH": 3.8,
   "IWD": 3.3,
   "IWA": 2.05,
   "PSH": 3.81,
   "PSD": 3.61,
   "PSA": 2.02,
   "WHH": 3.7,
   "WHD": 3.5,
   "WHA": 2,
   "VCH": 3.75,
   "VCD": 3.3,
   "VCA": 2,
   "MaxH": 3.98,
   "MaxD": 3.65,
   "MaxA": 2.1,
   "AvgH": 3.74,
   "AvgD": 3.48,
   "AvgA": 2.01,
   "B365>2.5": 2,
   "B365<2.5": 1.8,
   "P>2.5": 2,
   "P<2.5": 1.9,
   "Max>2.5": 2.08,
   "Max<2.5": 1.94,
   "Avg>2.5": 1.98,
   "Avg<2.5": 1.83,
   "AHh": 0.5,
   "B365AHH": 1.86,
   "B365AHA": 2.04,
   "PAHH": 1.9,
   "PAHA": 2.02,
   "MaxAHH": 1.9,
   "MaxAHA": 2.06,
   "AvgAHH": 1.84,
   "AvgAHA": 2.01,
   "B365CH": 4,
   "B365CD": 3.6,
   "B365CA": 1.9,
   "BWCH": 3.9,
   "BWCD": 3.5,
   "BWCA": 1.95,
   "IWCH": 4,
   "IWCD": 3.45,
   "IWCA": 1.95,
   "PSCH": 3.99,
   "PSCD": 3.74,
   "PSCA": 1.93,
   "WHCH": 4,
   "WHCD": 3.7,
   "WHCA": 1.85,
   "VCCH": 4.1,
   "VCCD": 3.6,
   "VCCA": 1.87,
   "MaxCH": 4.34,
   "MaxCD": 3.88,
   "MaxCA": 1.98,
   "AvgCH": 3.95,
   "AvgCD": 3.61,
   "AvgCA": 1.91,
   "B365C>2.5": 1.9,
   "B365C<2.5": 1.9,
   "PC>2.5": 1.93,
   "PC<2.5": 1.97,
   "MaxC>2.5": 1.99,
   "MaxC<2.5": 2.05,
   "AvgC>2.5": 1.89,
   "AvgC<2.5": 1.92,
   "AHCh": 0.5,
   "B365CAHH": 1.99,
   "B365CAHA": 1.91,
   "PCAHH": 1.99,
   "PCAHA": 1.93,
   "MaxCAHH": 2.01,
   "MaxCAHA": 1.95,
   "AvgCAHH": 1.94,
   "AvgCAHA": 1.91
 },
 {
   "Div": "F1",
   "Date": "30/08/2020",
   "Time": "14:00",
   "HomeTeam": "Nantes",
   "AwayTeam": "Nimes",
   "FTHG": 2,
   "FTAG": 1,
   "FTR": "H",
   "HTHG": 2,
   "HTAG": 0,
   "HTR": "H",
   "HS": 8,
   "AS": 17,
   "HST": 5,
   "AST": 9,
   "HF": 16,
   "AF": 9,
   "HC": 4,
   "AC": 8,
   "HY": 3,
   "AY": 2,
   "HR": 2,
   "AR": 0,
   "B365H": 1.95,
   "B365D": 3.2,
   "B365A": 4.2,
   "BWH": 1.91,
   "BWD": 3.3,
   "BWA": 4.5,
   "IWH": 2,
   "IWD": 3.1,
   "IWA": 4.2,
   "PSH": 1.99,
   "PSD": 3.27,
   "PSA": 4.42,
   "WHH": 1.91,
   "WHD": 3.25,
   "WHA": 4.33,
   "VCH": 1.93,
   "VCD": 3.2,
   "VCA": 4.2,
   "MaxH": 2.03,
   "MaxD": 3.44,
   "MaxA": 4.72,
   "AvgH": 1.96,
   "AvgD": 3.25,
   "AvgA": 4.28,
   "B365>2.5": 2.3,
   "B365<2.5": 1.61,
   "P>2.5": 2.4,
   "P<2.5": 1.63,
   "Max>2.5": 2.46,
   "Max<2.5": 1.68,
   "Avg>2.5": 2.32,
   "Avg<2.5": 1.61,
   "AHh": -0.5,
   "B365AHH": 1.98,
   "B365AHA": 1.92,
   "PAHH": 1.99,
   "PAHA": 1.93,
   "MaxAHH": 2.03,
   "MaxAHA": 1.95,
   "AvgAHH": 1.96,
   "AvgAHA": 1.88,
   "B365CH": 1.83,
   "B365CD": 3.4,
   "B365CA": 4.75,
   "BWCH": 1.91,
   "BWCD": 3.4,
   "BWCA": 4.33,
   "IWCH": 1.9,
   "IWCD": 3.25,
   "IWCA": 4.5,
   "PSCH": 1.93,
   "PSCD": 3.36,
   "PSCA": 4.58,
   "WHCH": 1.8,
   "WHCD": 3.4,
   "WHCA": 4.75,
   "VCCH": 1.83,
   "VCCD": 3.4,
   "VCCA": 4.5,
   "MaxCH": 2.02,
   "MaxCD": 3.54,
   "MaxCA": 5.1,
   "AvgCH": 1.9,
   "AvgCD": 3.36,
   "AvgCA": 4.43,
   "B365C>2.5": 2.2,
   "B365C<2.5": 1.66,
   "PC>2.5": 2.22,
   "PC<2.5": 1.73,
   "MaxC>2.5": 2.27,
   "MaxC<2.5": 1.78,
   "AvgC>2.5": 2.17,
   "AvgC<2.5": 1.69,
   "AHCh": -0.5,
   "B365CAHH": 1.91,
   "B365CAHA": 1.99,
   "PCAHH": 1.93,
   "PCAHA": 1.99,
   "MaxCAHH": 2.01,
   "MaxCAHA": 2.03,
   "AvgCAHH": 1.9,
   "AvgCAHA": 1.95
 },
 {
   "Div": "F1",
   "Date": "30/08/2020",
   "Time": "14:00",
   "HomeTeam": "St Etienne",
   "AwayTeam": "Lorient",
   "FTHG": 2,
   "FTAG": 0,
   "FTR": "H",
   "HTHG": 1,
   "HTAG": 0,
   "HTR": "H",
   "HS": 13,
   "AS": 6,
   "HST": 5,
   "AST": 1,
   "HF": 14,
   "AF": 23,
   "HC": 2,
   "AC": 5,
   "HY": 2,
   "AY": 1,
   "HR": 0,
   "AR": 0,
   "B365H": 2.2,
   "B365D": 3.2,
   "B365A": 3.4,
   "BWH": 2.3,
   "BWD": 3.2,
   "BWA": 3.3,
   "IWH": 2.3,
   "IWD": 3.05,
   "IWA": 3.3,
   "PSH": 2.3,
   "PSD": 3.28,
   "PSA": 3.35,
   "WHH": 2.25,
   "WHD": 3.3,
   "WHA": 3.25,
   "VCH": 2.25,
   "VCD": 3.13,
   "VCA": 3.3,
   "MaxH": 2.36,
   "MaxD": 3.46,
   "MaxA": 3.55,
   "AvgH": 2.27,
   "AvgD": 3.23,
   "AvgA": 3.29,
   "B365>2.5": 2.3,
   "B365<2.5": 1.61,
   "P>2.5": 2.28,
   "P<2.5": 1.69,
   "Max>2.5": 2.37,
   "Max<2.5": 1.73,
   "Avg>2.5": 2.25,
   "Avg<2.5": 1.64,
   "AHh": -0.25,
   "B365AHH": 1.96,
   "B365AHA": 1.94,
   "PAHH": 1.98,
   "PAHA": 1.93,
   "MaxAHH": 2,
   "MaxAHA": 1.96,
   "AvgAHH": 1.94,
   "AvgAHA": 1.91,
   "B365CH": 2.3,
   "B365CD": 3.2,
   "B365CA": 3.3,
   "BWCH": 2.3,
   "BWCD": 3.2,
   "BWCA": 3.3,
   "IWCH": 2.3,
   "IWCD": 3.05,
   "IWCA": 3.35,
   "PSCH": 2.31,
   "PSCD": 3.24,
   "PSCA": 3.37,
   "WHCH": 2.25,
   "WHCD": 3.2,
   "WHCA": 3.25,
   "VCCH": 2.25,
   "VCCD": 3.2,
   "VCCA": 3.3,
   "MaxCH": 2.4,
   "MaxCD": 3.35,
   "MaxCA": 3.5,
   "AvgCH": 2.29,
   "AvgCD": 3.21,
   "AvgCA": 3.3,
   "B365C>2.5": 2.2,
   "B365C<2.5": 1.66,
   "PC>2.5": 2.23,
   "PC<2.5": 1.72,
   "MaxC>2.5": 2.3,
   "MaxC<2.5": 1.77,
   "AvgC>2.5": 2.19,
   "AvgC<2.5": 1.68,
   "AHCh": -0.25,
   "B365CAHH": 1.97,
   "B365CAHA": 1.93,
   "PCAHH": 1.99,
   "PCAHA": 1.93,
   "MaxCAHH": 2.04,
   "MaxCAHA": 1.95,
   "AvgCAHH": 1.95,
   "AvgCAHA": 1.9
 },
 {
   "Div": "F1",
   "Date": "30/08/2020",
   "Time": "20:00",
   "HomeTeam": "Brest",
   "AwayTeam": "Marseille",
   "FTHG": 2,
   "FTAG": 3,
   "FTR": "A",
   "HTHG": 1,
   "HTAG": 2,
   "HTR": "A",
   "HS": 19,
   "AS": 7,
   "HST": 4,
   "AST": 4,
   "HF": 17,
   "AF": 13,
   "HC": 10,
   "AC": 2,
   "HY": 2,
   "AY": 4,
   "HR": 0,
   "AR": 0,
   "B365H": 3,
   "B365D": 3.5,
   "B365A": 2,
   "BWH": null,
   "BWD": null,
   "BWA": null,
   "IWH": 3.3,
   "IWD": 3.5,
   "IWA": 2.15,
   "PSH": null,
   "PSD": null,
   "PSA": null,
   "WHH": null,
   "WHD": null,
   "WHA": null,
   "VCH": null,
   "VCD": null,
   "VCA": null,
   "MaxH": 3.56,
   "MaxD": 3.85,
   "MaxA": 2.18,
   "AvgH": 3.36,
   "AvgD": 3.64,
   "AvgA": 2.09,
   "B365>2.5": 1.8,
   "B365<2.5": 2,
   "P>2.5": null,
   "P<2.5": null,
   "Max>2.5": 1.89,
   "Max<2.5": 2.11,
   "Avg>2.5": 1.79,
   "Avg<2.5": 2.01,
   "AHh": 0.25,
   "B365AHH": null,
   "B365AHA": null,
   "PAHH": null,
   "PAHA": null,
   "MaxAHH": 2.08,
   "MaxAHA": 1.84,
   "AvgAHH": 2.01,
   "AvgAHA": 1.82,
   "B365CH": 3.5,
   "B365CD": 3.2,
   "B365CA": 2.2,
   "BWCH": 3.5,
   "BWCD": 3.2,
   "BWCA": 2.2,
   "IWCH": 3.5,
   "IWCD": 3.15,
   "IWCA": 2.25,
   "PSCH": 3.67,
   "PSCD": 3.26,
   "PSCA": 2.23,
   "WHCH": 3.6,
   "WHCD": 3.1,
   "WHCA": 2.2,
   "VCCH": 3.5,
   "VCCD": 3.13,
   "VCCA": 2.2,
   "MaxCH": 4.65,
   "MaxCD": 3.8,
   "MaxCA": 2.33,
   "AvgCH": 3.6,
   "AvgCD": 3.21,
   "AvgCA": 2.18,
   "B365C>2.5": 2.37,
   "B365C<2.5": 1.57,
   "PC>2.5": 2.41,
   "PC<2.5": 1.63,
   "MaxC>2.5": 2.43,
   "MaxC<2.5": 1.7,
   "AvgC>2.5": 2.31,
   "AvgC<2.5": 1.62,
   "AHCh": 0.25,
   "B365CAHH": 1.99,
   "B365CAHA": 1.91,
   "PCAHH": 2.01,
   "PCAHA": 1.89,
   "MaxCAHH": 2.1,
   "MaxCAHA": 1.94,
   "AvgCAHH": 1.98,
   "AvgCAHA": 1.88
 }
]